text_models/__init__.py
text_models/dataset.py
text_models/model_selection.py
text_models/place.py
text_models/utils.py
text_models/vocabulary.py
text_models/data/CP.desc
text_models/data/CP.info
text_models/data/bbox.dict
text_models/data/bbox_coords.dict
text_models/data/bbox_country.dict
text_models/data/country-loc.ds
text_models/data/country.ds
text_models/data/emojis.dict
text_models/data/state.dict
text_models/tests/test_dataset.py
text_models/tests/test_model_selection.py
text_models/tests/test_place.py
text_models/tests/test_utils.py
text_models/tests/test_vocabulary.py
text_models/tests/tweets.json.gz
text_models-0.13.0.dist-info/LICENSE
text_models-0.13.0.dist-info/METADATA
text_models-0.13.0.dist-info/WHEEL
text_models-0.13.0.dist-info/top_level.txt
text_models-0.13.0.dist-info/RECORD
